README.md
setup.py
./accounts/__init__.py
./accounts/urls.py
./accounts/views.py
./accounts/templates/auth/login.html
./accounts/templates/auth/logout.html
./accounts/templates/mfa/_wizard_actions.html
./accounts/templates/mfa/backup_tokens.html
./accounts/templates/mfa/disable.html
./accounts/templates/mfa/phone_register.html
./accounts/templates/mfa/setup.html
./accounts/templates/mfa/setup_complete.html
./accounts/templates/password_management/password_change.html
./accounts/templates/password_management/password_change_done.html
./accounts/templates/password_management/password_reset.html
./accounts/templates/password_management/password_reset_complete.html
./accounts/templates/password_management/password_reset_confirm.html
./accounts/templates/password_management/password_reset_done.html
./accounts/templates/profile/settings.html
./accounts/templates/registration/activated.html
./accounts/templates/registration/closed.html
./accounts/templates/registration/complete.html
./accounts/templates/registration/form.html
./accounts/templates/registration/resend_activation.html
./accounts/templates/registration/resend_activation_complete.html
devenney_accounts.egg-info/PKG-INFO
devenney_accounts.egg-info/SOURCES.txt
devenney_accounts.egg-info/dependency_links.txt
devenney_accounts.egg-info/requires.txt
devenney_accounts.egg-info/top_level.txt