Metadata-Version: 1.0
Name: devenney-accounts
Version: 1.0.1
Summary: Elegant Django account management
Home-page: https://github.com/devenney/django_accounts
Author: Brendan Devenney
Author-email: brendan@devenney.io
License: MIT
Platform: UNKNOWN
